{
    "search_date": "2026-10-15",
    "recommendation_info": {
        "destination": "경주",
        "weather_summary": "10월 중순 경주는 전형적으로 맑고 쾌청하며 온화한 날씨를 보입니다. 평균 기온은 10~20°C 내외로 야외 활동하기에 매우 적합하며, 가을 단풍이 절정에 달하는 시기입니다.",
        "local_events": [
            "신라문화제 (Silla Culture Festival, 매년 10월 경)",
            "불국사, 보문호반길 등 주요 명소 단풍 절정"
        ],
        "recommendation_reason": "2026년 10월 15일은 경주의 가을 단풍이 절정에 달하는 시기로, 고즈넉한 신라 유적지와 어우러진 아름다운 풍경을 만끽하기에 최적입니다. 맑고 온화한 날씨 덕분에 불국사, 대릉원, 첨성대 등 야외 역사 유적지를 여유롭게 둘러보며 가을 정취를 온전히 느낄 수 있습니다. 또한, '신라문화제'와 같은 행사가 열린다면 더욱 풍성한 문화 체험이 가능하며, 붐비지 않는 선선한 가을 날씨 속에서 특별한 추억을 만들 수 있습니다."
    },
    "naver_restaurants": [
        {
            "name": "포석로 소갈비찜",
            "address": "경상북도 경주시 황남동 228-1",
            "category": "음식점>한식",
            "url": "https://www.instagram.com/poseok_ro",
            "x": "1292118391",
            "y": "358359027"
        },
        {
            "name": "큰기와 황리단길 본점",
            "address": "경상북도 경주시 사정동 116-2 1층",
            "category": "한식>육류,고기요리",
            "url": "",
            "x": "1292079072",
            "y": "358349813"
        },
        {
            "name": "우마왕 경주본점",
            "address": "경상북도 경주시 보문동 33-81",
            "category": "한식>갈비탕",
            "url": "https://smartstore.naver.com/woomawang",
            "x": "1292542505",
            "y": "358428658"
        },
        {
            "name": "청온채",
            "address": "경상북도 경주시 사정동 29-1 청온채",
            "category": "음식점>한식",
            "url": "https://app.catchtable.co.kr/ct/shop/cheongonchae",
            "x": "1292087986",
            "y": "358376216"
        },
        {
            "name": "황남빵",
            "address": "경상북도 경주시 황오동 347-1",
            "category": "카페,디저트>베이커리",
            "url": "https://hwangnam.com",
            "x": "1292136375",
            "y": "358408903"
        }
    ],
    "errors": []
}